README.md
setup.py
flask_records/__init__.py
flask_records/_compat.py
flask_records/_internals.py
flask_records/decorators.py
flask_records/errors.py
flask_records/flask_records.py
flask_records/patchs.py
flask_records/records_dao.py
flask_records.egg-info/PKG-INFO
flask_records.egg-info/SOURCES.txt
flask_records.egg-info/dependency_links.txt
flask_records.egg-info/requires.txt
flask_records.egg-info/top_level.txt